aioairzone/__init__.py
aioairzone/common.py
aioairzone/const.py
aioairzone/exceptions.py
aioairzone/hotwater.py
aioairzone/http.py
aioairzone/localapi.py
aioairzone/py.typed
aioairzone/system.py
aioairzone/thermostat.py
aioairzone/webserver.py
aioairzone/zone.py
aioairzone-1.0.4.dist-info/licenses/LICENSE
aioairzone-1.0.4.dist-info/METADATA
aioairzone-1.0.4.dist-info/WHEEL
aioairzone-1.0.4.dist-info/top_level.txt
aioairzone-1.0.4.dist-info/RECORD
