Metadata-Version: 2.4
Name: aioairzone
Version: 1.0.4
Summary: Library to control Airzone devices
Author-email: Álvaro Fernández Rojas <noltari@gmail.com>
License-Expression: Apache-2.0
Project-URL: Homepage, https://github.com/Noltari/aioairzone
Project-URL: Bug Tracker, https://github.com/Noltari/aioairzone/issues
Keywords: airzone,hvac,home
Platform: any
Classifier: Development Status :: 5 - Production/Stable
Classifier: Intended Audience :: Developers
Classifier: Natural Language :: English
Classifier: Programming Language :: Python :: 3
Classifier: Programming Language :: Python :: 3.12
Classifier: Programming Language :: Python :: 3.13
Classifier: Topic :: Home Automation
Requires-Python: >=3.12
License-File: LICENSE
Requires-Dist: aiohttp
Dynamic: license-file
